EBomb/__init__.py
EBomb/__main__.py
EBomb/_ua.py
EBomb/services.py
EBomb/services.txt
EBomb-2.2.2.dist-info/METADATA
EBomb-2.2.2.dist-info/WHEEL
EBomb-2.2.2.dist-info/top_level.txt
EBomb-2.2.2.dist-info/RECORD
