Metadata-Version: 2.1
Name: EBomb
Version: 2.2.2
Summary: Email Bomber
Home-page: https://github.com/NIKDISSV-Forever/EBomb
Author: Nikita (NIKDISSV)
Author-email: nikdissv@proton.me
License: UNKNOWN
Platform: UNKNOWN
Classifier: Programming Language :: Python :: 3.10
Classifier: Development Status :: 5 - Production/Stable
Classifier: License :: OSI Approved :: MIT License
Classifier: Operating System :: OS Independent
Classifier: Typing :: Typed
Requires-Python: >=3.8
Requires-Dist: httpx
Requires-Dist: httpx[socks]
Requires-Dist: EasyProxies
Requires-Dist: spys
Requires-Dist: fake-useragent
Requires-Dist: rich
